fi/aieval/__init__.py
fi/aieval/evaluator.py
fi/aieval/metrics/__init__.py
fi/aieval/metrics/aggregated_metric.py
fi/aieval/metrics/bleu.py
fi/aieval/metrics/embedding_similarity.py
fi/aieval/metrics/laveshtein.py
fi/aieval/metrics/numeric_diff.py
fi/aieval/metrics/rouge.py
fi/aieval/metrics/semantic_list_contains.py
fi/aieval/protect.py
fi/aieval/templates.py
fi/aieval/types.py
fi_aieval-0.1.0.dist-info/METADATA
fi_aieval-0.1.0.dist-info/WHEEL
fi_aieval-0.1.0.dist-info/RECORD
